txt_to_pickle/__init__.py
txt_to_pickle/__main__.py
txt_to_pickle/helpers.py
txt_to_pickle-0.0.1.dist-info/licenses/LICENSE
txt_to_pickle-0.0.1.dist-info/METADATA
txt_to_pickle-0.0.1.dist-info/WHEEL
txt_to_pickle-0.0.1.dist-info/entry_points.txt
txt_to_pickle-0.0.1.dist-info/top_level.txt
txt_to_pickle-0.0.1.dist-info/RECORD
