Metadata-Version: 2.4
Name: txt_to_pickle
Version: 0.0.1
Summary: Txt file to Pickle file
Author-email: Ka Wa Yip <yipkawa@gmail.com>
License: MIT License
Project-URL: Homepage, https://github.com/kwyip/txt_to_pickle
Project-URL: Issues, https://github.com/kwyip/txt_to_pickle/issues
Keywords: txt,pickle,conversion
Classifier: Programming Language :: Python
Classifier: Programming Language :: Python :: 3
Classifier: Programming Language :: Python :: 3.8
Classifier: Programming Language :: Python :: 3.9
Classifier: Programming Language :: Python :: 3.10
Classifier: Programming Language :: Python :: 3.11
Classifier: Programming Language :: Python :: 3.12
Classifier: Programming Language :: Python :: 3.13
Requires-Python: >=3.8
License-File: LICENSE
Provides-Extra: build
Requires-Dist: build; extra == "build"
Requires-Dist: twine; extra == "build"
Provides-Extra: dev
Requires-Dist: black; extra == "dev"
Requires-Dist: bumpver; extra == "dev"
Requires-Dist: isort; extra == "dev"
Requires-Dist: mypy; extra == "dev"
Requires-Dist: pytest; extra == "dev"
Dynamic: license-file
